<?xml version="1.0" standalone="yes"?>
<SourceScanResultsCache xmlns="http://tempuri.org/SourceScanResults.xsd">
  <SourceScanResults>
    <SourceScanID>1</SourceScanID>
    <ModuleName>DbFunctions.cs</ModuleName>
    <LineNumber>56</LineNumber>
    <ColumnNumber>46</ColumnNumber>
    <OriginalText>Database open connection</OriginalText>
    <IsHidden>false</IsHidden>
    <IndexOnLine>0</IndexOnLine>
    <StartOfStatement>56</StartOfStatement>
    <EndOfStatement>56</EndOfStatement>
    <IsVerbatim>false</IsVerbatim>
    <IsHiddenBlock>false</IsHiddenBlock>
    <CodeElement>Open</CodeElement>
    <RelativeLineNumber>16</RelativeLineNumber>
    <IsHiddenString>false</IsHiddenString>
    <IsInterpolatedString>false</IsInterpolatedString>
    <ClassName>PfsenseVoucherMgr.DbFunctions</ClassName>
    <IsController>false</IsController>
  </SourceScanResults>
  <SourceScanResults>
    <SourceScanID>2</SourceScanID>
    <ModuleName>DbFunctions.cs</ModuleName>
    <LineNumber>93</LineNumber>
    <ColumnNumber>20</ColumnNumber>
    <OriginalText>Select Count (*) from Users Where uName = '</OriginalText>
    <IsHidden>false</IsHidden>
    <IndexOnLine>0</IndexOnLine>
    <StartOfStatement>93</StartOfStatement>
    <EndOfStatement>93</EndOfStatement>
    <IsVerbatim>false</IsVerbatim>
    <IsHiddenBlock>false</IsHiddenBlock>
    <CodeElement>FindUser</CodeElement>
    <RelativeLineNumber>7</RelativeLineNumber>
    <IsHiddenString>false</IsHiddenString>
    <IsInterpolatedString>false</IsInterpolatedString>
    <ClassName>PfsenseVoucherMgr.DbFunctions</ClassName>
    <IsController>false</IsController>
  </SourceScanResults>
  <SourceScanResults>
    <SourceScanID>3</SourceScanID>
    <ModuleName>DbFunctions.cs</ModuleName>
    <LineNumber>104</LineNumber>
    <ColumnNumber>46</ColumnNumber>
    <OriginalText>Database find user</OriginalText>
    <IsHidden>false</IsHidden>
    <IndexOnLine>0</IndexOnLine>
    <StartOfStatement>104</StartOfStatement>
    <EndOfStatement>104</EndOfStatement>
    <IsVerbatim>false</IsVerbatim>
    <IsHiddenBlock>false</IsHiddenBlock>
    <CodeElement>FindUser</CodeElement>
    <RelativeLineNumber>18</RelativeLineNumber>
    <IsHiddenString>false</IsHiddenString>
    <IsInterpolatedString>false</IsInterpolatedString>
    <ClassName>PfsenseVoucherMgr.DbFunctions</ClassName>
    <IsController>false</IsController>
  </SourceScanResults>
  <SourceScanResults>
    <SourceScanID>4</SourceScanID>
    <ModuleName>DbFunctions.cs</ModuleName>
    <LineNumber>122</LineNumber>
    <ColumnNumber>20</ColumnNumber>
    <OriginalText>Select uID from Users Where uName = '</OriginalText>
    <IsHidden>false</IsHidden>
    <IndexOnLine>0</IndexOnLine>
    <StartOfStatement>122</StartOfStatement>
    <EndOfStatement>122</EndOfStatement>
    <IsVerbatim>false</IsVerbatim>
    <IsHiddenBlock>false</IsHiddenBlock>
    <CodeElement>GetUserID</CodeElement>
    <RelativeLineNumber>7</RelativeLineNumber>
    <IsHiddenString>false</IsHiddenString>
    <IsInterpolatedString>false</IsInterpolatedString>
    <ClassName>PfsenseVoucherMgr.DbFunctions</ClassName>
    <IsController>false</IsController>
  </SourceScanResults>
  <SourceScanResults>
    <SourceScanID>5</SourceScanID>
    <ModuleName>DbFunctions.cs</ModuleName>
    <LineNumber>133</LineNumber>
    <ColumnNumber>46</ColumnNumber>
    <OriginalText>Database get user id</OriginalText>
    <IsHidden>false</IsHidden>
    <IndexOnLine>0</IndexOnLine>
    <StartOfStatement>133</StartOfStatement>
    <EndOfStatement>133</EndOfStatement>
    <IsVerbatim>false</IsVerbatim>
    <IsHiddenBlock>false</IsHiddenBlock>
    <CodeElement>GetUserID</CodeElement>
    <RelativeLineNumber>18</RelativeLineNumber>
    <IsHiddenString>false</IsHiddenString>
    <IsInterpolatedString>false</IsInterpolatedString>
    <ClassName>PfsenseVoucherMgr.DbFunctions</ClassName>
    <IsController>false</IsController>
  </SourceScanResults>
  <SourceScanResults>
    <SourceScanID>6</SourceScanID>
    <ModuleName>DbFunctions.cs</ModuleName>
    <LineNumber>148</LineNumber>
    <ColumnNumber>20</ColumnNumber>
    <OriginalText>Select uAdminStatus from Users Where uName = '</OriginalText>
    <IsHidden>false</IsHidden>
    <IndexOnLine>0</IndexOnLine>
    <StartOfStatement>148</StartOfStatement>
    <EndOfStatement>148</EndOfStatement>
    <IsVerbatim>false</IsVerbatim>
    <IsHiddenBlock>false</IsHiddenBlock>
    <CodeElement>GetAdminStatus</CodeElement>
    <RelativeLineNumber>7</RelativeLineNumber>
    <IsHiddenString>false</IsHiddenString>
    <IsInterpolatedString>false</IsInterpolatedString>
    <ClassName>PfsenseVoucherMgr.DbFunctions</ClassName>
    <IsController>false</IsController>
  </SourceScanResults>
  <SourceScanResults>
    <SourceScanID>7</SourceScanID>
    <ModuleName>DbFunctions.cs</ModuleName>
    <LineNumber>157</LineNumber>
    <ColumnNumber>46</ColumnNumber>
    <OriginalText>Database get user AdminStatus</OriginalText>
    <IsHidden>false</IsHidden>
    <IndexOnLine>0</IndexOnLine>
    <StartOfStatement>157</StartOfStatement>
    <EndOfStatement>157</EndOfStatement>
    <IsVerbatim>false</IsVerbatim>
    <IsHiddenBlock>false</IsHiddenBlock>
    <CodeElement>GetAdminStatus</CodeElement>
    <RelativeLineNumber>16</RelativeLineNumber>
    <IsHiddenString>false</IsHiddenString>
    <IsInterpolatedString>false</IsInterpolatedString>
    <ClassName>PfsenseVoucherMgr.DbFunctions</ClassName>
    <IsController>false</IsController>
  </SourceScanResults>
  <SourceScanResults>
    <SourceScanID>8</SourceScanID>
    <ModuleName>DbFunctions.cs</ModuleName>
    <LineNumber>181</LineNumber>
    <ColumnNumber>20</ColumnNumber>
    <OriginalText>Insert into Users( uName, uAdminStatus, uCDate ) values( '</OriginalText>
    <IsHidden>false</IsHidden>
    <IndexOnLine>0</IndexOnLine>
    <StartOfStatement>181</StartOfStatement>
    <EndOfStatement>181</EndOfStatement>
    <IsVerbatim>false</IsVerbatim>
    <IsHiddenBlock>false</IsHiddenBlock>
    <CodeElement>InsertUser</CodeElement>
    <RelativeLineNumber>7</RelativeLineNumber>
    <IsHiddenString>false</IsHiddenString>
    <IsInterpolatedString>false</IsInterpolatedString>
    <ClassName>PfsenseVoucherMgr.DbFunctions</ClassName>
    <IsController>false</IsController>
  </SourceScanResults>
  <SourceScanResults>
    <SourceScanID>9</SourceScanID>
    <ModuleName>DbFunctions.cs</ModuleName>
    <LineNumber>181</LineNumber>
    <ColumnNumber>134</ColumnNumber>
    <OriginalText>yyyy-MM-dd HH:mm:ss</OriginalText>
    <IsHidden>false</IsHidden>
    <IndexOnLine>1</IndexOnLine>
    <StartOfStatement>181</StartOfStatement>
    <EndOfStatement>181</EndOfStatement>
    <IsVerbatim>false</IsVerbatim>
    <IsHiddenBlock>false</IsHiddenBlock>
    <CodeElement>InsertUser</CodeElement>
    <RelativeLineNumber>7</RelativeLineNumber>
    <IsHiddenString>false</IsHiddenString>
    <IsInterpolatedString>false</IsInterpolatedString>
    <ClassName>PfsenseVoucherMgr.DbFunctions</ClassName>
    <IsController>false</IsController>
  </SourceScanResults>
  <SourceScanResults>
    <SourceScanID>10</SourceScanID>
    <ModuleName>DbFunctions.cs</ModuleName>
    <LineNumber>192</LineNumber>
    <ColumnNumber>46</ColumnNumber>
    <OriginalText>Database insert user</OriginalText>
    <IsHidden>false</IsHidden>
    <IndexOnLine>0</IndexOnLine>
    <StartOfStatement>192</StartOfStatement>
    <EndOfStatement>192</EndOfStatement>
    <IsVerbatim>false</IsVerbatim>
    <IsHiddenBlock>false</IsHiddenBlock>
    <CodeElement>InsertUser</CodeElement>
    <RelativeLineNumber>18</RelativeLineNumber>
    <IsHiddenString>false</IsHiddenString>
    <IsInterpolatedString>false</IsInterpolatedString>
    <ClassName>PfsenseVoucherMgr.DbFunctions</ClassName>
    <IsController>false</IsController>
  </SourceScanResults>
  <SourceScanResults>
    <SourceScanID>11</SourceScanID>
    <ModuleName>DbFunctions.cs</ModuleName>
    <LineNumber>208</LineNumber>
    <ColumnNumber>20</ColumnNumber>
    <OriginalText>SELECT [uId],  [uName] FROM Users Where uName = '</OriginalText>
    <IsHidden>false</IsHidden>
    <IndexOnLine>0</IndexOnLine>
    <StartOfStatement>208</StartOfStatement>
    <EndOfStatement>208</EndOfStatement>
    <IsVerbatim>false</IsVerbatim>
    <IsHiddenBlock>false</IsHiddenBlock>
    <CodeElement>GetUserId</CodeElement>
    <RelativeLineNumber>8</RelativeLineNumber>
    <IsHiddenString>false</IsHiddenString>
    <IsInterpolatedString>false</IsInterpolatedString>
    <ClassName>PfsenseVoucherMgr.DbFunctions</ClassName>
    <IsController>false</IsController>
  </SourceScanResults>
  <SourceScanResults>
    <SourceScanID>12</SourceScanID>
    <ModuleName>DbFunctions.cs</ModuleName>
    <LineNumber>221</LineNumber>
    <ColumnNumber>46</ColumnNumber>
    <OriginalText>Database get ID of user</OriginalText>
    <IsHidden>false</IsHidden>
    <IndexOnLine>0</IndexOnLine>
    <StartOfStatement>221</StartOfStatement>
    <EndOfStatement>221</EndOfStatement>
    <IsVerbatim>false</IsVerbatim>
    <IsHiddenBlock>false</IsHiddenBlock>
    <CodeElement>GetUserId</CodeElement>
    <RelativeLineNumber>21</RelativeLineNumber>
    <IsHiddenString>false</IsHiddenString>
    <IsInterpolatedString>false</IsInterpolatedString>
    <ClassName>PfsenseVoucherMgr.DbFunctions</ClassName>
    <IsController>false</IsController>
  </SourceScanResults>
  <SourceScanResults>
    <SourceScanID>13</SourceScanID>
    <ModuleName>DbFunctions.cs</ModuleName>
    <LineNumber>242</LineNumber>
    <ColumnNumber>20</ColumnNumber>
    <OriginalText>Insert into Vouchers( vCode, vRoll, vImportDate, vImportUser ) values( '</OriginalText>
    <IsHidden>false</IsHidden>
    <IndexOnLine>0</IndexOnLine>
    <StartOfStatement>242</StartOfStatement>
    <EndOfStatement>242</EndOfStatement>
    <IsVerbatim>false</IsVerbatim>
    <IsHiddenBlock>false</IsHiddenBlock>
    <CodeElement>InsertVoucher</CodeElement>
    <RelativeLineNumber>8</RelativeLineNumber>
    <IsHiddenString>false</IsHiddenString>
    <IsInterpolatedString>false</IsInterpolatedString>
    <ClassName>PfsenseVoucherMgr.DbFunctions</ClassName>
    <IsController>false</IsController>
  </SourceScanResults>
  <SourceScanResults>
    <SourceScanID>14</SourceScanID>
    <ModuleName>DbFunctions.cs</ModuleName>
    <LineNumber>242</LineNumber>
    <ColumnNumber>143</ColumnNumber>
    <OriginalText>yyyy - MM - dd HH: mm: ss</OriginalText>
    <IsHidden>false</IsHidden>
    <IndexOnLine>1</IndexOnLine>
    <StartOfStatement>242</StartOfStatement>
    <EndOfStatement>242</EndOfStatement>
    <IsVerbatim>false</IsVerbatim>
    <IsHiddenBlock>false</IsHiddenBlock>
    <CodeElement>InsertVoucher</CodeElement>
    <RelativeLineNumber>8</RelativeLineNumber>
    <IsHiddenString>false</IsHiddenString>
    <IsInterpolatedString>false</IsInterpolatedString>
    <ClassName>PfsenseVoucherMgr.DbFunctions</ClassName>
    <IsController>false</IsController>
  </SourceScanResults>
  <SourceScanResults>
    <SourceScanID>15</SourceScanID>
    <ModuleName>DbFunctions.cs</ModuleName>
    <LineNumber>252</LineNumber>
    <ColumnNumber>46</ColumnNumber>
    <OriginalText>Database insert voucher</OriginalText>
    <IsHidden>false</IsHidden>
    <IndexOnLine>0</IndexOnLine>
    <StartOfStatement>252</StartOfStatement>
    <EndOfStatement>252</EndOfStatement>
    <IsVerbatim>false</IsVerbatim>
    <IsHiddenBlock>false</IsHiddenBlock>
    <CodeElement>InsertVoucher</CodeElement>
    <RelativeLineNumber>18</RelativeLineNumber>
    <IsHiddenString>false</IsHiddenString>
    <IsInterpolatedString>false</IsInterpolatedString>
    <ClassName>PfsenseVoucherMgr.DbFunctions</ClassName>
    <IsController>false</IsController>
  </SourceScanResults>
  <SourceScanResults>
    <SourceScanID>16</SourceScanID>
    <ModuleName>DbFunctions.cs</ModuleName>
    <LineNumber>265</LineNumber>
    <ColumnNumber>20</ColumnNumber>
    <OriginalText>Select Count (*) from Vouchers Where vSpendDate is NUll</OriginalText>
    <IsHidden>false</IsHidden>
    <IndexOnLine>0</IndexOnLine>
    <StartOfStatement>265</StartOfStatement>
    <EndOfStatement>265</EndOfStatement>
    <IsVerbatim>false</IsVerbatim>
    <IsHiddenBlock>false</IsHiddenBlock>
    <CodeElement>CountFreeVouchers</CodeElement>
    <RelativeLineNumber>7</RelativeLineNumber>
    <IsHiddenString>false</IsHiddenString>
    <IsInterpolatedString>false</IsInterpolatedString>
    <ClassName>PfsenseVoucherMgr.DbFunctions</ClassName>
    <IsController>false</IsController>
  </SourceScanResults>
  <SourceScanResults>
    <SourceScanID>17</SourceScanID>
    <ModuleName>DbFunctions.cs</ModuleName>
    <LineNumber>274</LineNumber>
    <ColumnNumber>46</ColumnNumber>
    <OriginalText>Database count free vouchers</OriginalText>
    <IsHidden>false</IsHidden>
    <IndexOnLine>0</IndexOnLine>
    <StartOfStatement>274</StartOfStatement>
    <EndOfStatement>274</EndOfStatement>
    <IsVerbatim>false</IsVerbatim>
    <IsHiddenBlock>false</IsHiddenBlock>
    <CodeElement>CountFreeVouchers</CodeElement>
    <RelativeLineNumber>16</RelativeLineNumber>
    <IsHiddenString>false</IsHiddenString>
    <IsInterpolatedString>false</IsInterpolatedString>
    <ClassName>PfsenseVoucherMgr.DbFunctions</ClassName>
    <IsController>false</IsController>
  </SourceScanResults>
  <SourceScanResults>
    <SourceScanID>18</SourceScanID>
    <ModuleName>DbFunctions.cs</ModuleName>
    <LineNumber>290</LineNumber>
    <ColumnNumber>20</ColumnNumber>
    <OriginalText>SELECT TOP 1 [vId],[vCode] from Vouchers Where vSpendDate is NUll</OriginalText>
    <IsHidden>false</IsHidden>
    <IndexOnLine>0</IndexOnLine>
    <StartOfStatement>290</StartOfStatement>
    <EndOfStatement>290</EndOfStatement>
    <IsVerbatim>false</IsVerbatim>
    <IsHiddenBlock>false</IsHiddenBlock>
    <CodeElement>GetOneFreeVoucherId</CodeElement>
    <RelativeLineNumber>8</RelativeLineNumber>
    <IsHiddenString>false</IsHiddenString>
    <IsInterpolatedString>false</IsInterpolatedString>
    <ClassName>PfsenseVoucherMgr.DbFunctions</ClassName>
    <IsController>false</IsController>
  </SourceScanResults>
  <SourceScanResults>
    <SourceScanID>19</SourceScanID>
    <ModuleName>DbFunctions.cs</ModuleName>
    <LineNumber>303</LineNumber>
    <ColumnNumber>46</ColumnNumber>
    <OriginalText>Database get ID of one free voucher</OriginalText>
    <IsHidden>false</IsHidden>
    <IndexOnLine>0</IndexOnLine>
    <StartOfStatement>303</StartOfStatement>
    <EndOfStatement>303</EndOfStatement>
    <IsVerbatim>false</IsVerbatim>
    <IsHiddenBlock>false</IsHiddenBlock>
    <CodeElement>GetOneFreeVoucherId</CodeElement>
    <RelativeLineNumber>21</RelativeLineNumber>
    <IsHiddenString>false</IsHiddenString>
    <IsInterpolatedString>false</IsInterpolatedString>
    <ClassName>PfsenseVoucherMgr.DbFunctions</ClassName>
    <IsController>false</IsController>
  </SourceScanResults>
  <SourceScanResults>
    <SourceScanID>20</SourceScanID>
    <ModuleName>DbFunctions.cs</ModuleName>
    <LineNumber>320</LineNumber>
    <ColumnNumber>20</ColumnNumber>
    <OriginalText>SELECT [vCode] from Vouchers Where vId = </OriginalText>
    <IsHidden>false</IsHidden>
    <IndexOnLine>0</IndexOnLine>
    <StartOfStatement>320</StartOfStatement>
    <EndOfStatement>320</EndOfStatement>
    <IsVerbatim>false</IsVerbatim>
    <IsHiddenBlock>false</IsHiddenBlock>
    <CodeElement>GetVoucherCode</CodeElement>
    <RelativeLineNumber>8</RelativeLineNumber>
    <IsHiddenString>false</IsHiddenString>
    <IsInterpolatedString>false</IsInterpolatedString>
    <ClassName>PfsenseVoucherMgr.DbFunctions</ClassName>
    <IsController>false</IsController>
  </SourceScanResults>
  <SourceScanResults>
    <SourceScanID>21</SourceScanID>
    <ModuleName>DbFunctions.cs</ModuleName>
    <LineNumber>333</LineNumber>
    <ColumnNumber>46</ColumnNumber>
    <OriginalText>Database get voucher code</OriginalText>
    <IsHidden>false</IsHidden>
    <IndexOnLine>0</IndexOnLine>
    <StartOfStatement>333</StartOfStatement>
    <EndOfStatement>333</EndOfStatement>
    <IsVerbatim>false</IsVerbatim>
    <IsHiddenBlock>false</IsHiddenBlock>
    <CodeElement>GetVoucherCode</CodeElement>
    <RelativeLineNumber>21</RelativeLineNumber>
    <IsHiddenString>false</IsHiddenString>
    <IsInterpolatedString>false</IsInterpolatedString>
    <ClassName>PfsenseVoucherMgr.DbFunctions</ClassName>
    <IsController>false</IsController>
  </SourceScanResults>
  <SourceScanResults>
    <SourceScanID>22</SourceScanID>
    <ModuleName>DbFunctions.cs</ModuleName>
    <LineNumber>351</LineNumber>
    <ColumnNumber>20</ColumnNumber>
    <OriginalText>Update Vouchers set vSpendUser = </OriginalText>
    <IsHidden>false</IsHidden>
    <IndexOnLine>0</IndexOnLine>
    <StartOfStatement>351</StartOfStatement>
    <EndOfStatement>351</EndOfStatement>
    <IsVerbatim>false</IsVerbatim>
    <IsHiddenBlock>false</IsHiddenBlock>
    <CodeElement>UpdateVoucher</CodeElement>
    <RelativeLineNumber>9</RelativeLineNumber>
    <IsHiddenString>false</IsHiddenString>
    <IsInterpolatedString>false</IsInterpolatedString>
    <ClassName>PfsenseVoucherMgr.DbFunctions</ClassName>
    <IsController>false</IsController>
  </SourceScanResults>
  <SourceScanResults>
    <SourceScanID>23</SourceScanID>
    <ModuleName>DbFunctions.cs</ModuleName>
    <LineNumber>351</LineNumber>
    <ColumnNumber>71</ColumnNumber>
    <OriginalText>, vSpendToUser = '</OriginalText>
    <IsHidden>false</IsHidden>
    <IndexOnLine>1</IndexOnLine>
    <StartOfStatement>351</StartOfStatement>
    <EndOfStatement>351</EndOfStatement>
    <IsVerbatim>false</IsVerbatim>
    <IsHiddenBlock>false</IsHiddenBlock>
    <CodeElement>UpdateVoucher</CodeElement>
    <RelativeLineNumber>9</RelativeLineNumber>
    <IsHiddenString>false</IsHiddenString>
    <IsInterpolatedString>false</IsInterpolatedString>
    <ClassName>PfsenseVoucherMgr.DbFunctions</ClassName>
    <IsController>false</IsController>
  </SourceScanResults>
  <SourceScanResults>
    <SourceScanID>24</SourceScanID>
    <ModuleName>DbFunctions.cs</ModuleName>
    <LineNumber>351</LineNumber>
    <ColumnNumber>109</ColumnNumber>
    <OriginalText>', vSpendDate = '</OriginalText>
    <IsHidden>false</IsHidden>
    <IndexOnLine>2</IndexOnLine>
    <StartOfStatement>351</StartOfStatement>
    <EndOfStatement>351</EndOfStatement>
    <IsVerbatim>false</IsVerbatim>
    <IsHiddenBlock>false</IsHiddenBlock>
    <CodeElement>UpdateVoucher</CodeElement>
    <RelativeLineNumber>9</RelativeLineNumber>
    <IsHiddenString>false</IsHiddenString>
    <IsInterpolatedString>false</IsInterpolatedString>
    <ClassName>PfsenseVoucherMgr.DbFunctions</ClassName>
    <IsController>false</IsController>
  </SourceScanResults>
  <SourceScanResults>
    <SourceScanID>25</SourceScanID>
    <ModuleName>DbFunctions.cs</ModuleName>
    <LineNumber>351</LineNumber>
    <ColumnNumber>144</ColumnNumber>
    <OriginalText>yyyy - MM - dd HH: mm: ss</OriginalText>
    <IsHidden>false</IsHidden>
    <IndexOnLine>3</IndexOnLine>
    <StartOfStatement>351</StartOfStatement>
    <EndOfStatement>351</EndOfStatement>
    <IsVerbatim>false</IsVerbatim>
    <IsHiddenBlock>false</IsHiddenBlock>
    <CodeElement>UpdateVoucher</CodeElement>
    <RelativeLineNumber>9</RelativeLineNumber>
    <IsHiddenString>false</IsHiddenString>
    <IsInterpolatedString>false</IsInterpolatedString>
    <ClassName>PfsenseVoucherMgr.DbFunctions</ClassName>
    <IsController>false</IsController>
  </SourceScanResults>
  <SourceScanResults>
    <SourceScanID>26</SourceScanID>
    <ModuleName>DbFunctions.cs</ModuleName>
    <LineNumber>351</LineNumber>
    <ColumnNumber>175</ColumnNumber>
    <OriginalText>' Where vId = </OriginalText>
    <IsHidden>false</IsHidden>
    <IndexOnLine>4</IndexOnLine>
    <StartOfStatement>351</StartOfStatement>
    <EndOfStatement>351</EndOfStatement>
    <IsVerbatim>false</IsVerbatim>
    <IsHiddenBlock>false</IsHiddenBlock>
    <CodeElement>UpdateVoucher</CodeElement>
    <RelativeLineNumber>9</RelativeLineNumber>
    <IsHiddenString>false</IsHiddenString>
    <IsInterpolatedString>false</IsInterpolatedString>
    <ClassName>PfsenseVoucherMgr.DbFunctions</ClassName>
    <IsController>false</IsController>
  </SourceScanResults>
  <SourceScanResults>
    <SourceScanID>27</SourceScanID>
    <ModuleName>DbFunctions.cs</ModuleName>
    <LineNumber>363</LineNumber>
    <ColumnNumber>46</ColumnNumber>
    <OriginalText>Database update voucher</OriginalText>
    <IsHidden>false</IsHidden>
    <IndexOnLine>0</IndexOnLine>
    <StartOfStatement>363</StartOfStatement>
    <EndOfStatement>363</EndOfStatement>
    <IsVerbatim>false</IsVerbatim>
    <IsHiddenBlock>false</IsHiddenBlock>
    <CodeElement>UpdateVoucher</CodeElement>
    <RelativeLineNumber>21</RelativeLineNumber>
    <IsHiddenString>false</IsHiddenString>
    <IsInterpolatedString>false</IsInterpolatedString>
    <ClassName>PfsenseVoucherMgr.DbFunctions</ClassName>
    <IsController>false</IsController>
  </SourceScanResults>
  <SourceScanResults>
    <SourceScanID>28</SourceScanID>
    <ModuleName>DbFunctions.cs</ModuleName>
    <LineNumber>374</LineNumber>
    <ColumnNumber>40</ColumnNumber>
    <OriginalText>char</OriginalText>
    <IsHidden>false</IsHidden>
    <IndexOnLine>0</IndexOnLine>
    <StartOfStatement>373</StartOfStatement>
    <EndOfStatement>374</EndOfStatement>
    <IsVerbatim>false</IsVerbatim>
    <IsHiddenBlock>false</IsHiddenBlock>
    <CodeElement>CheckForSQLInjection</CodeElement>
    <RelativeLineNumber>5</RelativeLineNumber>
    <IsHiddenString>false</IsHiddenString>
    <IsInterpolatedString>false</IsInterpolatedString>
    <ClassName>PfsenseVoucherMgr.DbFunctions</ClassName>
    <IsController>false</IsController>
  </SourceScanResults>
  <SourceScanResults>
    <SourceScanID>29</SourceScanID>
    <ModuleName>DbFunctions.cs</ModuleName>
    <LineNumber>374</LineNumber>
    <ColumnNumber>48</ColumnNumber>
    <OriginalText>nchar</OriginalText>
    <IsHidden>false</IsHidden>
    <IndexOnLine>4</IndexOnLine>
    <StartOfStatement>373</StartOfStatement>
    <EndOfStatement>374</EndOfStatement>
    <IsVerbatim>false</IsVerbatim>
    <IsHiddenBlock>false</IsHiddenBlock>
    <CodeElement>CheckForSQLInjection</CodeElement>
    <RelativeLineNumber>5</RelativeLineNumber>
    <IsHiddenString>false</IsHiddenString>
    <IsInterpolatedString>false</IsInterpolatedString>
    <ClassName>PfsenseVoucherMgr.DbFunctions</ClassName>
    <IsController>false</IsController>
  </SourceScanResults>
  <SourceScanResults>
    <SourceScanID>30</SourceScanID>
    <ModuleName>DbFunctions.cs</ModuleName>
    <LineNumber>374</LineNumber>
    <ColumnNumber>57</ColumnNumber>
    <OriginalText>varchar</OriginalText>
    <IsHidden>false</IsHidden>
    <IndexOnLine>8</IndexOnLine>
    <StartOfStatement>373</StartOfStatement>
    <EndOfStatement>374</EndOfStatement>
    <IsVerbatim>false</IsVerbatim>
    <IsHiddenBlock>false</IsHiddenBlock>
    <CodeElement>CheckForSQLInjection</CodeElement>
    <RelativeLineNumber>5</RelativeLineNumber>
    <IsHiddenString>false</IsHiddenString>
    <IsInterpolatedString>false</IsInterpolatedString>
    <ClassName>PfsenseVoucherMgr.DbFunctions</ClassName>
    <IsController>false</IsController>
  </SourceScanResults>
  <SourceScanResults>
    <SourceScanID>31</SourceScanID>
    <ModuleName>DbFunctions.cs</ModuleName>
    <LineNumber>374</LineNumber>
    <ColumnNumber>68</ColumnNumber>
    <OriginalText>nvarchar</OriginalText>
    <IsHidden>false</IsHidden>
    <IndexOnLine>14</IndexOnLine>
    <StartOfStatement>373</StartOfStatement>
    <EndOfStatement>374</EndOfStatement>
    <IsVerbatim>false</IsVerbatim>
    <IsHiddenBlock>false</IsHiddenBlock>
    <CodeElement>CheckForSQLInjection</CodeElement>
    <RelativeLineNumber>5</RelativeLineNumber>
    <IsHiddenString>false</IsHiddenString>
    <IsInterpolatedString>false</IsInterpolatedString>
    <ClassName>PfsenseVoucherMgr.DbFunctions</ClassName>
    <IsController>false</IsController>
  </SourceScanResults>
  <SourceScanResults>
    <SourceScanID>32</SourceScanID>
    <ModuleName>DbFunctions.cs</ModuleName>
    <LineNumber>375</LineNumber>
    <ColumnNumber>40</ColumnNumber>
    <OriginalText>alter</OriginalText>
    <IsHidden>false</IsHidden>
    <IndexOnLine>1</IndexOnLine>
    <StartOfStatement>373</StartOfStatement>
    <EndOfStatement>375</EndOfStatement>
    <IsVerbatim>false</IsVerbatim>
    <IsHiddenBlock>false</IsHiddenBlock>
    <CodeElement>CheckForSQLInjection</CodeElement>
    <RelativeLineNumber>6</RelativeLineNumber>
    <IsHiddenString>false</IsHiddenString>
    <IsInterpolatedString>false</IsInterpolatedString>
    <ClassName>PfsenseVoucherMgr.DbFunctions</ClassName>
    <IsController>false</IsController>
  </SourceScanResults>
  <SourceScanResults>
    <SourceScanID>33</SourceScanID>
    <ModuleName>DbFunctions.cs</ModuleName>
    <LineNumber>375</LineNumber>
    <ColumnNumber>49</ColumnNumber>
    <OriginalText>begin</OriginalText>
    <IsHidden>false</IsHidden>
    <IndexOnLine>5</IndexOnLine>
    <StartOfStatement>373</StartOfStatement>
    <EndOfStatement>375</EndOfStatement>
    <IsVerbatim>false</IsVerbatim>
    <IsHiddenBlock>false</IsHiddenBlock>
    <CodeElement>CheckForSQLInjection</CodeElement>
    <RelativeLineNumber>6</RelativeLineNumber>
    <IsHiddenString>false</IsHiddenString>
    <IsInterpolatedString>false</IsInterpolatedString>
    <ClassName>PfsenseVoucherMgr.DbFunctions</ClassName>
    <IsController>false</IsController>
  </SourceScanResults>
  <SourceScanResults>
    <SourceScanID>34</SourceScanID>
    <ModuleName>DbFunctions.cs</ModuleName>
    <LineNumber>375</LineNumber>
    <ColumnNumber>58</ColumnNumber>
    <OriginalText>cast</OriginalText>
    <IsHidden>false</IsHidden>
    <IndexOnLine>9</IndexOnLine>
    <StartOfStatement>373</StartOfStatement>
    <EndOfStatement>375</EndOfStatement>
    <IsVerbatim>false</IsVerbatim>
    <IsHiddenBlock>false</IsHiddenBlock>
    <CodeElement>CheckForSQLInjection</CodeElement>
    <RelativeLineNumber>6</RelativeLineNumber>
    <IsHiddenString>false</IsHiddenString>
    <IsInterpolatedString>false</IsInterpolatedString>
    <ClassName>PfsenseVoucherMgr.DbFunctions</ClassName>
    <IsController>false</IsController>
  </SourceScanResults>
  <SourceScanResults>
    <SourceScanID>35</SourceScanID>
    <ModuleName>DbFunctions.cs</ModuleName>
    <LineNumber>375</LineNumber>
    <ColumnNumber>66</ColumnNumber>
    <OriginalText>create</OriginalText>
    <IsHidden>false</IsHidden>
    <IndexOnLine>13</IndexOnLine>
    <StartOfStatement>373</StartOfStatement>
    <EndOfStatement>375</EndOfStatement>
    <IsVerbatim>false</IsVerbatim>
    <IsHiddenBlock>false</IsHiddenBlock>
    <CodeElement>CheckForSQLInjection</CodeElement>
    <RelativeLineNumber>6</RelativeLineNumber>
    <IsHiddenString>false</IsHiddenString>
    <IsInterpolatedString>false</IsInterpolatedString>
    <ClassName>PfsenseVoucherMgr.DbFunctions</ClassName>
    <IsController>false</IsController>
  </SourceScanResults>
  <SourceScanResults>
    <SourceScanID>36</SourceScanID>
    <ModuleName>DbFunctions.cs</ModuleName>
    <LineNumber>375</LineNumber>
    <ColumnNumber>76</ColumnNumber>
    <OriginalText>cursor</OriginalText>
    <IsHidden>false</IsHidden>
    <IndexOnLine>18</IndexOnLine>
    <StartOfStatement>373</StartOfStatement>
    <EndOfStatement>375</EndOfStatement>
    <IsVerbatim>false</IsVerbatim>
    <IsHiddenBlock>false</IsHiddenBlock>
    <CodeElement>CheckForSQLInjection</CodeElement>
    <RelativeLineNumber>6</RelativeLineNumber>
    <IsHiddenString>false</IsHiddenString>
    <IsInterpolatedString>false</IsInterpolatedString>
    <ClassName>PfsenseVoucherMgr.DbFunctions</ClassName>
    <IsController>false</IsController>
  </SourceScanResults>
  <SourceScanResults>
    <SourceScanID>37</SourceScanID>
    <ModuleName>DbFunctions.cs</ModuleName>
    <LineNumber>375</LineNumber>
    <ColumnNumber>86</ColumnNumber>
    <OriginalText>declare</OriginalText>
    <IsHidden>false</IsHidden>
    <IndexOnLine>20</IndexOnLine>
    <StartOfStatement>373</StartOfStatement>
    <EndOfStatement>375</EndOfStatement>
    <IsVerbatim>false</IsVerbatim>
    <IsHiddenBlock>false</IsHiddenBlock>
    <CodeElement>CheckForSQLInjection</CodeElement>
    <RelativeLineNumber>6</RelativeLineNumber>
    <IsHiddenString>false</IsHiddenString>
    <IsInterpolatedString>false</IsInterpolatedString>
    <ClassName>PfsenseVoucherMgr.DbFunctions</ClassName>
    <IsController>false</IsController>
  </SourceScanResults>
  <SourceScanResults>
    <SourceScanID>38</SourceScanID>
    <ModuleName>DbFunctions.cs</ModuleName>
    <LineNumber>376</LineNumber>
    <ColumnNumber>40</ColumnNumber>
    <OriginalText>delete</OriginalText>
    <IsHidden>false</IsHidden>
    <IndexOnLine>2</IndexOnLine>
    <StartOfStatement>373</StartOfStatement>
    <EndOfStatement>376</EndOfStatement>
    <IsVerbatim>false</IsVerbatim>
    <IsHiddenBlock>false</IsHiddenBlock>
    <CodeElement>CheckForSQLInjection</CodeElement>
    <RelativeLineNumber>7</RelativeLineNumber>
    <IsHiddenString>false</IsHiddenString>
    <IsInterpolatedString>false</IsInterpolatedString>
    <ClassName>PfsenseVoucherMgr.DbFunctions</ClassName>
    <IsController>false</IsController>
  </SourceScanResults>
  <SourceScanResults>
    <SourceScanID>39</SourceScanID>
    <ModuleName>DbFunctions.cs</ModuleName>
    <LineNumber>376</LineNumber>
    <ColumnNumber>50</ColumnNumber>
    <OriginalText>drop</OriginalText>
    <IsHidden>false</IsHidden>
    <IndexOnLine>6</IndexOnLine>
    <StartOfStatement>373</StartOfStatement>
    <EndOfStatement>376</EndOfStatement>
    <IsVerbatim>false</IsVerbatim>
    <IsHiddenBlock>false</IsHiddenBlock>
    <CodeElement>CheckForSQLInjection</CodeElement>
    <RelativeLineNumber>7</RelativeLineNumber>
    <IsHiddenString>false</IsHiddenString>
    <IsInterpolatedString>false</IsInterpolatedString>
    <ClassName>PfsenseVoucherMgr.DbFunctions</ClassName>
    <IsController>false</IsController>
  </SourceScanResults>
  <SourceScanResults>
    <SourceScanID>40</SourceScanID>
    <ModuleName>DbFunctions.cs</ModuleName>
    <LineNumber>376</LineNumber>
    <ColumnNumber>58</ColumnNumber>
    <OriginalText>end</OriginalText>
    <IsHidden>false</IsHidden>
    <IndexOnLine>10</IndexOnLine>
    <StartOfStatement>373</StartOfStatement>
    <EndOfStatement>376</EndOfStatement>
    <IsVerbatim>false</IsVerbatim>
    <IsHiddenBlock>false</IsHiddenBlock>
    <CodeElement>CheckForSQLInjection</CodeElement>
    <RelativeLineNumber>7</RelativeLineNumber>
    <IsHiddenString>false</IsHiddenString>
    <IsInterpolatedString>false</IsInterpolatedString>
    <ClassName>PfsenseVoucherMgr.DbFunctions</ClassName>
    <IsController>false</IsController>
  </SourceScanResults>
  <SourceScanResults>
    <SourceScanID>41</SourceScanID>
    <ModuleName>DbFunctions.cs</ModuleName>
    <LineNumber>376</LineNumber>
    <ColumnNumber>65</ColumnNumber>
    <OriginalText>exec</OriginalText>
    <IsHidden>false</IsHidden>
    <IndexOnLine>12</IndexOnLine>
    <StartOfStatement>373</StartOfStatement>
    <EndOfStatement>376</EndOfStatement>
    <IsVerbatim>false</IsVerbatim>
    <IsHiddenBlock>false</IsHiddenBlock>
    <CodeElement>CheckForSQLInjection</CodeElement>
    <RelativeLineNumber>7</RelativeLineNumber>
    <IsHiddenString>false</IsHiddenString>
    <IsInterpolatedString>false</IsInterpolatedString>
    <ClassName>PfsenseVoucherMgr.DbFunctions</ClassName>
    <IsController>false</IsController>
  </SourceScanResults>
  <SourceScanResults>
    <SourceScanID>42</SourceScanID>
    <ModuleName>DbFunctions.cs</ModuleName>
    <LineNumber>376</LineNumber>
    <ColumnNumber>73</ColumnNumber>
    <OriginalText>execute</OriginalText>
    <IsHidden>false</IsHidden>
    <IndexOnLine>16</IndexOnLine>
    <StartOfStatement>373</StartOfStatement>
    <EndOfStatement>376</EndOfStatement>
    <IsVerbatim>false</IsVerbatim>
    <IsHiddenBlock>false</IsHiddenBlock>
    <CodeElement>CheckForSQLInjection</CodeElement>
    <RelativeLineNumber>7</RelativeLineNumber>
    <IsHiddenString>false</IsHiddenString>
    <IsInterpolatedString>false</IsInterpolatedString>
    <ClassName>PfsenseVoucherMgr.DbFunctions</ClassName>
    <IsController>false</IsController>
  </SourceScanResults>
  <SourceScanResults>
    <SourceScanID>43</SourceScanID>
    <ModuleName>DbFunctions.cs</ModuleName>
    <LineNumber>376</LineNumber>
    <ColumnNumber>84</ColumnNumber>
    <OriginalText>fetch</OriginalText>
    <IsHidden>false</IsHidden>
    <IndexOnLine>19</IndexOnLine>
    <StartOfStatement>373</StartOfStatement>
    <EndOfStatement>376</EndOfStatement>
    <IsVerbatim>false</IsVerbatim>
    <IsHiddenBlock>false</IsHiddenBlock>
    <CodeElement>CheckForSQLInjection</CodeElement>
    <RelativeLineNumber>7</RelativeLineNumber>
    <IsHiddenString>false</IsHiddenString>
    <IsInterpolatedString>false</IsInterpolatedString>
    <ClassName>PfsenseVoucherMgr.DbFunctions</ClassName>
    <IsController>false</IsController>
  </SourceScanResults>
  <SourceScanResults>
    <SourceScanID>44</SourceScanID>
    <ModuleName>DbFunctions.cs</ModuleName>
    <LineNumber>377</LineNumber>
    <ColumnNumber>40</ColumnNumber>
    <OriginalText>insert</OriginalText>
    <IsHidden>false</IsHidden>
    <IndexOnLine>3</IndexOnLine>
    <StartOfStatement>373</StartOfStatement>
    <EndOfStatement>377</EndOfStatement>
    <IsVerbatim>false</IsVerbatim>
    <IsHiddenBlock>false</IsHiddenBlock>
    <CodeElement>CheckForSQLInjection</CodeElement>
    <RelativeLineNumber>8</RelativeLineNumber>
    <IsHiddenString>false</IsHiddenString>
    <IsInterpolatedString>false</IsInterpolatedString>
    <ClassName>PfsenseVoucherMgr.DbFunctions</ClassName>
    <IsController>false</IsController>
  </SourceScanResults>
  <SourceScanResults>
    <SourceScanID>45</SourceScanID>
    <ModuleName>DbFunctions.cs</ModuleName>
    <LineNumber>377</LineNumber>
    <ColumnNumber>50</ColumnNumber>
    <OriginalText>kill</OriginalText>
    <IsHidden>false</IsHidden>
    <IndexOnLine>7</IndexOnLine>
    <StartOfStatement>373</StartOfStatement>
    <EndOfStatement>377</EndOfStatement>
    <IsVerbatim>false</IsVerbatim>
    <IsHiddenBlock>false</IsHiddenBlock>
    <CodeElement>CheckForSQLInjection</CodeElement>
    <RelativeLineNumber>8</RelativeLineNumber>
    <IsHiddenString>false</IsHiddenString>
    <IsInterpolatedString>false</IsInterpolatedString>
    <ClassName>PfsenseVoucherMgr.DbFunctions</ClassName>
    <IsController>false</IsController>
  </SourceScanResults>
  <SourceScanResults>
    <SourceScanID>46</SourceScanID>
    <ModuleName>DbFunctions.cs</ModuleName>
    <LineNumber>377</LineNumber>
    <ColumnNumber>58</ColumnNumber>
    <OriginalText>select</OriginalText>
    <IsHidden>false</IsHidden>
    <IndexOnLine>11</IndexOnLine>
    <StartOfStatement>373</StartOfStatement>
    <EndOfStatement>377</EndOfStatement>
    <IsVerbatim>false</IsVerbatim>
    <IsHiddenBlock>false</IsHiddenBlock>
    <CodeElement>CheckForSQLInjection</CodeElement>
    <RelativeLineNumber>8</RelativeLineNumber>
    <IsHiddenString>false</IsHiddenString>
    <IsInterpolatedString>false</IsInterpolatedString>
    <ClassName>PfsenseVoucherMgr.DbFunctions</ClassName>
    <IsController>false</IsController>
  </SourceScanResults>
  <SourceScanResults>
    <SourceScanID>47</SourceScanID>
    <ModuleName>DbFunctions.cs</ModuleName>
    <LineNumber>377</LineNumber>
    <ColumnNumber>68</ColumnNumber>
    <OriginalText>sys</OriginalText>
    <IsHidden>false</IsHidden>
    <IndexOnLine>15</IndexOnLine>
    <StartOfStatement>373</StartOfStatement>
    <EndOfStatement>377</EndOfStatement>
    <IsVerbatim>false</IsVerbatim>
    <IsHiddenBlock>false</IsHiddenBlock>
    <CodeElement>CheckForSQLInjection</CodeElement>
    <RelativeLineNumber>8</RelativeLineNumber>
    <IsHiddenString>false</IsHiddenString>
    <IsInterpolatedString>false</IsInterpolatedString>
    <ClassName>PfsenseVoucherMgr.DbFunctions</ClassName>
    <IsController>false</IsController>
  </SourceScanResults>
  <SourceScanResults>
    <SourceScanID>48</SourceScanID>
    <ModuleName>DbFunctions.cs</ModuleName>
    <LineNumber>377</LineNumber>
    <ColumnNumber>75</ColumnNumber>
    <OriginalText>sysobjects</OriginalText>
    <IsHidden>false</IsHidden>
    <IndexOnLine>17</IndexOnLine>
    <StartOfStatement>373</StartOfStatement>
    <EndOfStatement>377</EndOfStatement>
    <IsVerbatim>false</IsVerbatim>
    <IsHiddenBlock>false</IsHiddenBlock>
    <CodeElement>CheckForSQLInjection</CodeElement>
    <RelativeLineNumber>8</RelativeLineNumber>
    <IsHiddenString>false</IsHiddenString>
    <IsInterpolatedString>false</IsInterpolatedString>
    <ClassName>PfsenseVoucherMgr.DbFunctions</ClassName>
    <IsController>false</IsController>
  </SourceScanResults>
  <SourceScanResults>
    <SourceScanID>49</SourceScanID>
    <ModuleName>DbFunctions.cs</ModuleName>
    <LineNumber>377</LineNumber>
    <ColumnNumber>89</ColumnNumber>
    <OriginalText>syscolumns</OriginalText>
    <IsHidden>false</IsHidden>
    <IndexOnLine>21</IndexOnLine>
    <StartOfStatement>373</StartOfStatement>
    <EndOfStatement>377</EndOfStatement>
    <IsVerbatim>false</IsVerbatim>
    <IsHiddenBlock>false</IsHiddenBlock>
    <CodeElement>CheckForSQLInjection</CodeElement>
    <RelativeLineNumber>8</RelativeLineNumber>
    <IsHiddenString>false</IsHiddenString>
    <IsInterpolatedString>false</IsInterpolatedString>
    <ClassName>PfsenseVoucherMgr.DbFunctions</ClassName>
    <IsController>false</IsController>
  </SourceScanResults>
  <SourceScanResults>
    <SourceScanID>50</SourceScanID>
    <ModuleName>DbFunctions.cs</ModuleName>
    <LineNumber>378</LineNumber>
    <ColumnNumber>40</ColumnNumber>
    <OriginalText>table</OriginalText>
    <IsHidden>false</IsHidden>
    <IndexOnLine>0</IndexOnLine>
    <StartOfStatement>378</StartOfStatement>
    <EndOfStatement>378</EndOfStatement>
    <IsVerbatim>false</IsVerbatim>
    <IsHiddenBlock>false</IsHiddenBlock>
    <CodeElement>CheckForSQLInjection</CodeElement>
    <RelativeLineNumber>9</RelativeLineNumber>
    <IsHiddenString>false</IsHiddenString>
    <IsInterpolatedString>false</IsInterpolatedString>
    <ClassName>PfsenseVoucherMgr.DbFunctions</ClassName>
    <IsController>false</IsController>
  </SourceScanResults>
  <SourceScanResults>
    <SourceScanID>51</SourceScanID>
    <ModuleName>DbFunctions.cs</ModuleName>
    <LineNumber>378</LineNumber>
    <ColumnNumber>49</ColumnNumber>
    <OriginalText>update</OriginalText>
    <IsHidden>false</IsHidden>
    <IndexOnLine>1</IndexOnLine>
    <StartOfStatement>378</StartOfStatement>
    <EndOfStatement>378</EndOfStatement>
    <IsVerbatim>false</IsVerbatim>
    <IsHiddenBlock>false</IsHiddenBlock>
    <CodeElement>CheckForSQLInjection</CodeElement>
    <RelativeLineNumber>9</RelativeLineNumber>
    <IsHiddenString>false</IsHiddenString>
    <IsInterpolatedString>false</IsInterpolatedString>
    <ClassName>PfsenseVoucherMgr.DbFunctions</ClassName>
    <IsController>false</IsController>
  </SourceScanResults>
  <SourceScanResults>
    <SourceScanID>52</SourceScanID>
    <ModuleName>frmAbout.cs</ModuleName>
    <LineNumber>45</LineNumber>
    <ColumnNumber>40</ColumnNumber>
    <OriginalText>About {0}</OriginalText>
    <IsHidden>false</IsHidden>
    <IndexOnLine>0</IndexOnLine>
    <StartOfStatement>45</StartOfStatement>
    <EndOfStatement>45</EndOfStatement>
    <IsVerbatim>false</IsVerbatim>
    <IsHiddenBlock>false</IsHiddenBlock>
    <CodeElement />
    <RelativeLineNumber>45</RelativeLineNumber>
    <IsHiddenString>false</IsHiddenString>
    <IsInterpolatedString>false</IsInterpolatedString>
    <ClassName>PfsenseVoucherMgr.frmAbout</ClassName>
    <IsController>false</IsController>
  </SourceScanResults>
  <SourceScanResults>
    <SourceScanID>53</SourceScanID>
    <ModuleName>frmAbout.cs</ModuleName>
    <LineNumber>47</LineNumber>
    <ColumnNumber>53</ColumnNumber>
    <OriginalText>Version {0}</OriginalText>
    <IsHidden>false</IsHidden>
    <IndexOnLine>0</IndexOnLine>
    <StartOfStatement>47</StartOfStatement>
    <EndOfStatement>47</EndOfStatement>
    <IsVerbatim>false</IsVerbatim>
    <IsHiddenBlock>false</IsHiddenBlock>
    <CodeElement />
    <RelativeLineNumber>47</RelativeLineNumber>
    <IsHiddenString>false</IsHiddenString>
    <IsInterpolatedString>false</IsInterpolatedString>
    <ClassName>PfsenseVoucherMgr.frmAbout</ClassName>
    <IsController>false</IsController>
  </SourceScanResults>
  <SourceScanResults>
    <SourceScanID>54</SourceScanID>
    <ModuleName>frmImport.cs</ModuleName>
    <LineNumber>97</LineNumber>
    <ColumnNumber>54</ColumnNumber>
    <OriginalText> vouchers imported</OriginalText>
    <IsHidden>false</IsHidden>
    <IndexOnLine>0</IndexOnLine>
    <StartOfStatement>97</StartOfStatement>
    <EndOfStatement>97</EndOfStatement>
    <IsVerbatim>false</IsVerbatim>
    <IsHiddenBlock>false</IsHiddenBlock>
    <CodeElement>btnImport_Click</CodeElement>
    <RelativeLineNumber>30</RelativeLineNumber>
    <IsHiddenString>false</IsHiddenString>
    <IsInterpolatedString>false</IsInterpolatedString>
    <ClassName>PfsenseVoucherMgr.frmImport</ClassName>
    <IsController>false</IsController>
  </SourceScanResults>
  <SourceScanResults>
    <SourceScanID>55</SourceScanID>
    <ModuleName>frmImport.cs</ModuleName>
    <LineNumber>97</LineNumber>
    <ColumnNumber>76</ColumnNumber>
    <OriginalText>Voucher import</OriginalText>
    <IsHidden>false</IsHidden>
    <IndexOnLine>1</IndexOnLine>
    <StartOfStatement>97</StartOfStatement>
    <EndOfStatement>97</EndOfStatement>
    <IsVerbatim>false</IsVerbatim>
    <IsHiddenBlock>false</IsHiddenBlock>
    <CodeElement>btnImport_Click</CodeElement>
    <RelativeLineNumber>30</RelativeLineNumber>
    <IsHiddenString>false</IsHiddenString>
    <IsInterpolatedString>false</IsInterpolatedString>
    <ClassName>PfsenseVoucherMgr.frmImport</ClassName>
    <IsController>false</IsController>
  </SourceScanResults>
  <SourceScanResults>
    <SourceScanID>56</SourceScanID>
    <ModuleName>frmImport.cs</ModuleName>
    <LineNumber>117</LineNumber>
    <ColumnNumber>38</ColumnNumber>
    <OriginalText>C:\</OriginalText>
    <IsHidden>false</IsHidden>
    <IndexOnLine>3</IndexOnLine>
    <StartOfStatement>116</StartOfStatement>
    <EndOfStatement>117</EndOfStatement>
    <IsVerbatim>true</IsVerbatim>
    <IsHiddenBlock>false</IsHiddenBlock>
    <CodeElement>btnSelectFile_Click</CodeElement>
    <RelativeLineNumber>5</RelativeLineNumber>
    <IsHiddenString>false</IsHiddenString>
    <IsInterpolatedString>false</IsInterpolatedString>
    <ClassName>PfsenseVoucherMgr.frmImport</ClassName>
    <IsController>false</IsController>
  </SourceScanResults>
  <SourceScanResults>
    <SourceScanID>57</SourceScanID>
    <ModuleName>frmImport.cs</ModuleName>
    <LineNumber>118</LineNumber>
    <ColumnNumber>26</ColumnNumber>
    <OriginalText>Browse for pfsence CSV files</OriginalText>
    <IsHidden>false</IsHidden>
    <IndexOnLine>0</IndexOnLine>
    <StartOfStatement>116</StartOfStatement>
    <EndOfStatement>118</EndOfStatement>
    <IsVerbatim>false</IsVerbatim>
    <IsHiddenBlock>false</IsHiddenBlock>
    <CodeElement>btnSelectFile_Click</CodeElement>
    <RelativeLineNumber>6</RelativeLineNumber>
    <IsHiddenString>false</IsHiddenString>
    <IsInterpolatedString>false</IsInterpolatedString>
    <ClassName>PfsenseVoucherMgr.frmImport</ClassName>
    <IsController>false</IsController>
  </SourceScanResults>
  <SourceScanResults>
    <SourceScanID>58</SourceScanID>
    <ModuleName>frmImport.cs</ModuleName>
    <LineNumber>119</LineNumber>
    <ColumnNumber>31</ColumnNumber>
    <OriginalText>csv</OriginalText>
    <IsHidden>false</IsHidden>
    <IndexOnLine>2</IndexOnLine>
    <StartOfStatement>116</StartOfStatement>
    <EndOfStatement>119</EndOfStatement>
    <IsVerbatim>false</IsVerbatim>
    <IsHiddenBlock>false</IsHiddenBlock>
    <CodeElement>btnSelectFile_Click</CodeElement>
    <RelativeLineNumber>7</RelativeLineNumber>
    <IsHiddenString>false</IsHiddenString>
    <IsInterpolatedString>false</IsInterpolatedString>
    <ClassName>PfsenseVoucherMgr.frmImport</ClassName>
    <IsController>false</IsController>
  </SourceScanResults>
  <SourceScanResults>
    <SourceScanID>59</SourceScanID>
    <ModuleName>frmImport.cs</ModuleName>
    <LineNumber>120</LineNumber>
    <ColumnNumber>27</ColumnNumber>
    <OriginalText>CSV files (*.csv)|*.csv</OriginalText>
    <IsHidden>false</IsHidden>
    <IndexOnLine>1</IndexOnLine>
    <StartOfStatement>116</StartOfStatement>
    <EndOfStatement>120</EndOfStatement>
    <IsVerbatim>false</IsVerbatim>
    <IsHiddenBlock>false</IsHiddenBlock>
    <CodeElement>btnSelectFile_Click</CodeElement>
    <RelativeLineNumber>8</RelativeLineNumber>
    <IsHiddenString>false</IsHiddenString>
    <IsInterpolatedString>false</IsInterpolatedString>
    <ClassName>PfsenseVoucherMgr.frmImport</ClassName>
    <IsController>false</IsController>
  </SourceScanResults>
  <SourceScanResults>
    <SourceScanID>60</SourceScanID>
    <ModuleName>frmMain.cs</ModuleName>
    <LineNumber>112</LineNumber>
    <ColumnNumber>46</ColumnNumber>
    <OriginalText>Database close connection</OriginalText>
    <IsHidden>false</IsHidden>
    <IndexOnLine>0</IndexOnLine>
    <StartOfStatement>112</StartOfStatement>
    <EndOfStatement>112</EndOfStatement>
    <IsVerbatim>false</IsVerbatim>
    <IsHiddenBlock>false</IsHiddenBlock>
    <CodeElement>frmMain_FormClosing</CodeElement>
    <RelativeLineNumber>10</RelativeLineNumber>
    <IsHiddenString>false</IsHiddenString>
    <IsInterpolatedString>false</IsInterpolatedString>
    <ClassName>PfsenseVoucherMgr.frmMain</ClassName>
    <IsController>false</IsController>
  </SourceScanResults>
  <SourceScanResults>
    <SourceScanID>61</SourceScanID>
    <ModuleName>frmMain.cs</ModuleName>
    <LineNumber>123</LineNumber>
    <ColumnNumber>34</ColumnNumber>
    <OriginalText>Please enter min. 10 characters !</OriginalText>
    <IsHidden>false</IsHidden>
    <IndexOnLine>0</IndexOnLine>
    <StartOfStatement>123</StartOfStatement>
    <EndOfStatement>123</EndOfStatement>
    <IsVerbatim>false</IsVerbatim>
    <IsHiddenBlock>false</IsHiddenBlock>
    <CodeElement>btnRequestVoucher_Click</CodeElement>
    <RelativeLineNumber>7</RelativeLineNumber>
    <IsHiddenString>false</IsHiddenString>
    <IsInterpolatedString>false</IsInterpolatedString>
    <ClassName>PfsenseVoucherMgr.frmMain</ClassName>
    <IsController>false</IsController>
  </SourceScanResults>
  <SourceScanResults>
    <SourceScanID>62</SourceScanID>
    <ModuleName>frmMain.cs</ModuleName>
    <LineNumber>127</LineNumber>
    <ColumnNumber>34</ColumnNumber>
    <OriginalText>Text contains not allowed strings !</OriginalText>
    <IsHidden>false</IsHidden>
    <IndexOnLine>0</IndexOnLine>
    <StartOfStatement>127</StartOfStatement>
    <EndOfStatement>127</EndOfStatement>
    <IsVerbatim>false</IsVerbatim>
    <IsHiddenBlock>false</IsHiddenBlock>
    <CodeElement>btnRequestVoucher_Click</CodeElement>
    <RelativeLineNumber>11</RelativeLineNumber>
    <IsHiddenString>false</IsHiddenString>
    <IsInterpolatedString>false</IsInterpolatedString>
    <ClassName>PfsenseVoucherMgr.frmMain</ClassName>
    <IsController>false</IsController>
  </SourceScanResults>
  <SourceScanResults>
    <SourceScanID>63</SourceScanID>
    <ModuleName>frmMain.cs</ModuleName>
    <LineNumber>185</LineNumber>
    <ColumnNumber>39</ColumnNumber>
    <OriginalText>Unused vouchers: </OriginalText>
    <IsHidden>false</IsHidden>
    <IndexOnLine>0</IndexOnLine>
    <StartOfStatement>185</StartOfStatement>
    <EndOfStatement>185</EndOfStatement>
    <IsVerbatim>false</IsVerbatim>
    <IsHiddenBlock>false</IsHiddenBlock>
    <CodeElement>UpdateUnusedVoucherHint</CodeElement>
    <RelativeLineNumber>11</RelativeLineNumber>
    <IsHiddenString>false</IsHiddenString>
    <IsInterpolatedString>false</IsInterpolatedString>
    <ClassName>PfsenseVoucherMgr.frmMain</ClassName>
    <IsController>false</IsController>
  </SourceScanResults>
  <SourceScanResults>
    <SourceScanID>64</SourceScanID>
    <ModuleName>frmMain.cs</ModuleName>
    <LineNumber>197</LineNumber>
    <ColumnNumber>48</ColumnNumber>
    <OriginalText>Database: opened</OriginalText>
    <IsHidden>false</IsHidden>
    <IndexOnLine>0</IndexOnLine>
    <StartOfStatement>197</StartOfStatement>
    <EndOfStatement>197</EndOfStatement>
    <IsVerbatim>false</IsVerbatim>
    <IsHiddenBlock>false</IsHiddenBlock>
    <CodeElement>frmMain_Refresh</CodeElement>
    <RelativeLineNumber>9</RelativeLineNumber>
    <IsHiddenString>false</IsHiddenString>
    <IsInterpolatedString>false</IsInterpolatedString>
    <ClassName>PfsenseVoucherMgr.frmMain</ClassName>
    <IsController>false</IsController>
  </SourceScanResults>
  <SourceScanResults>
    <SourceScanID>65</SourceScanID>
    <ModuleName>frmMain.cs</ModuleName>
    <LineNumber>207</LineNumber>
    <ColumnNumber>44</ColumnNumber>
    <OriginalText>Current user: </OriginalText>
    <IsHidden>false</IsHidden>
    <IndexOnLine>0</IndexOnLine>
    <StartOfStatement>207</StartOfStatement>
    <EndOfStatement>207</EndOfStatement>
    <IsVerbatim>false</IsVerbatim>
    <IsHiddenBlock>false</IsHiddenBlock>
    <CodeElement>frmMain_Refresh</CodeElement>
    <RelativeLineNumber>19</RelativeLineNumber>
    <IsHiddenString>false</IsHiddenString>
    <IsInterpolatedString>false</IsInterpolatedString>
    <ClassName>PfsenseVoucherMgr.frmMain</ClassName>
    <IsController>false</IsController>
  </SourceScanResults>
  <SourceScanResults>
    <SourceScanID>66</SourceScanID>
    <ModuleName>frmMain.cs</ModuleName>
    <LineNumber>221</LineNumber>
    <ColumnNumber>48</ColumnNumber>
    <OriginalText>Database: closed</OriginalText>
    <IsHidden>false</IsHidden>
    <IndexOnLine>0</IndexOnLine>
    <StartOfStatement>221</StartOfStatement>
    <EndOfStatement>221</EndOfStatement>
    <IsVerbatim>false</IsVerbatim>
    <IsHiddenBlock>false</IsHiddenBlock>
    <CodeElement>frmMain_Refresh</CodeElement>
    <RelativeLineNumber>33</RelativeLineNumber>
    <IsHiddenString>false</IsHiddenString>
    <IsInterpolatedString>false</IsInterpolatedString>
    <ClassName>PfsenseVoucherMgr.frmMain</ClassName>
    <IsController>false</IsController>
  </SourceScanResults>
  <SourceScanResults>
    <SourceScanID>67</SourceScanID>
    <ModuleName>frmSettings.cs</ModuleName>
    <LineNumber>91</LineNumber>
    <ColumnNumber>43</ColumnNumber>
    <StringID>1</StringID>
    <OriginalText>The language change will take full effect the next time you start the program.</OriginalText>
    <IsHidden>false</IsHidden>
    <IndexOnLine>0</IndexOnLine>
    <StartOfStatement>91</StartOfStatement>
    <EndOfStatement>91</EndOfStatement>
    <IsVerbatim>false</IsVerbatim>
    <IsHiddenBlock>false</IsHiddenBlock>
    <CodeElement>btnOk_Click</CodeElement>
    <RelativeLineNumber>13</RelativeLineNumber>
    <NamedResource>RES_ID_CultureChange</NamedResource>
    <IsHiddenString>false</IsHiddenString>
    <IsInterpolatedString>false</IsInterpolatedString>
    <ClassName>PfsenseVoucherMgr.frmSettings</ClassName>
    <IsController>false</IsController>
  </SourceScanResults>
  <SourceScanResults>
    <SourceScanID>68</SourceScanID>
    <ModuleName>frmSettings.cs</ModuleName>
    <LineNumber>91</LineNumber>
    <ColumnNumber>87</ColumnNumber>
    <OriginalText>Pfsense Voucher Manager</OriginalText>
    <IsHidden>false</IsHidden>
    <IndexOnLine>1</IndexOnLine>
    <StartOfStatement>91</StartOfStatement>
    <EndOfStatement>91</EndOfStatement>
    <IsVerbatim>false</IsVerbatim>
    <IsHiddenBlock>false</IsHiddenBlock>
    <CodeElement>btnOk_Click</CodeElement>
    <RelativeLineNumber>13</RelativeLineNumber>
    <IsHiddenString>false</IsHiddenString>
    <IsInterpolatedString>false</IsInterpolatedString>
    <ClassName>PfsenseVoucherMgr.frmSettings</ClassName>
    <IsController>false</IsController>
  </SourceScanResults>
  <SourceScanResults>
    <SourceScanID>69</SourceScanID>
    <ModuleName>frmSettings.cs</ModuleName>
    <LineNumber>109</LineNumber>
    <ColumnNumber>34</ColumnNumber>
    <OriginalText>Connection test successful.</OriginalText>
    <IsHidden>false</IsHidden>
    <IndexOnLine>0</IndexOnLine>
    <StartOfStatement>109</StartOfStatement>
    <EndOfStatement>109</EndOfStatement>
    <IsVerbatim>false</IsVerbatim>
    <IsHiddenBlock>false</IsHiddenBlock>
    <CodeElement>btnCheckDbConnction_Click</CodeElement>
    <RelativeLineNumber>8</RelativeLineNumber>
    <IsHiddenString>false</IsHiddenString>
    <IsInterpolatedString>false</IsInterpolatedString>
    <ClassName>PfsenseVoucherMgr.frmSettings</ClassName>
    <IsController>false</IsController>
  </SourceScanResults>
  <SourceScanResults>
    <SourceScanID>70</SourceScanID>
    <ModuleName>frmSettings.cs</ModuleName>
    <LineNumber>109</LineNumber>
    <ColumnNumber>65</ColumnNumber>
    <OriginalText>Check Database Connection</OriginalText>
    <IsHidden>false</IsHidden>
    <IndexOnLine>1</IndexOnLine>
    <StartOfStatement>109</StartOfStatement>
    <EndOfStatement>109</EndOfStatement>
    <IsVerbatim>false</IsVerbatim>
    <IsHiddenBlock>false</IsHiddenBlock>
    <CodeElement>btnCheckDbConnction_Click</CodeElement>
    <RelativeLineNumber>8</RelativeLineNumber>
    <IsHiddenString>false</IsHiddenString>
    <IsInterpolatedString>false</IsInterpolatedString>
    <ClassName>PfsenseVoucherMgr.frmSettings</ClassName>
    <IsController>false</IsController>
  </SourceScanResults>
  <SourceScanResults>
    <SourceScanID>71</SourceScanID>
    <ModuleName>frmShowVoucher.cs</ModuleName>
    <LineNumber>61</LineNumber>
    <ColumnNumber>31</ColumnNumber>
    <OriginalText>Voucher code for: </OriginalText>
    <IsHidden>false</IsHidden>
    <IndexOnLine>0</IndexOnLine>
    <StartOfStatement>61</StartOfStatement>
    <EndOfStatement>61</EndOfStatement>
    <IsVerbatim>false</IsVerbatim>
    <IsHiddenBlock>false</IsHiddenBlock>
    <CodeElement>frmShowVoucher_Load</CodeElement>
    <RelativeLineNumber>2</RelativeLineNumber>
    <IsHiddenString>false</IsHiddenString>
    <IsInterpolatedString>false</IsInterpolatedString>
    <ClassName>PfsenseVoucherMgr.frmShowVoucher</ClassName>
    <IsController>false</IsController>
  </SourceScanResults>
  <SourceScanResults>
    <SourceScanID>72</SourceScanID>
    <ModuleName>frmShowVoucher.cs</ModuleName>
    <LineNumber>63</LineNumber>
    <ColumnNumber>33</ColumnNumber>
    <OriginalText>Generated by: </OriginalText>
    <IsHidden>false</IsHidden>
    <IndexOnLine>0</IndexOnLine>
    <StartOfStatement>63</StartOfStatement>
    <EndOfStatement>63</EndOfStatement>
    <IsVerbatim>false</IsVerbatim>
    <IsHiddenBlock>false</IsHiddenBlock>
    <CodeElement>frmShowVoucher_Load</CodeElement>
    <RelativeLineNumber>4</RelativeLineNumber>
    <IsHiddenString>false</IsHiddenString>
    <IsInterpolatedString>false</IsInterpolatedString>
    <ClassName>PfsenseVoucherMgr.frmShowVoucher</ClassName>
    <IsController>false</IsController>
  </SourceScanResults>
  <SourceScanResults>
    <SourceScanID>73</SourceScanID>
    <ModuleName>frmShowVoucher.cs</ModuleName>
    <LineNumber>96</LineNumber>
    <ColumnNumber>36</ColumnNumber>
    <OriginalText>Voucher code for:</OriginalText>
    <IsHidden>false</IsHidden>
    <IndexOnLine>0</IndexOnLine>
    <StartOfStatement>96</StartOfStatement>
    <EndOfStatement>96</EndOfStatement>
    <IsVerbatim>false</IsVerbatim>
    <IsHiddenBlock>false</IsHiddenBlock>
    <CodeElement>PrnDoc_PrintPage</CodeElement>
    <RelativeLineNumber>14</RelativeLineNumber>
    <IsHiddenString>false</IsHiddenString>
    <IsInterpolatedString>false</IsInterpolatedString>
    <ClassName>PfsenseVoucherMgr.frmShowVoucher</ClassName>
    <IsController>false</IsController>
  </SourceScanResults>
  <SourceScanResults>
    <SourceScanID>74</SourceScanID>
    <ModuleName>frmShowVoucher.cs</ModuleName>
    <LineNumber>97</LineNumber>
    <ColumnNumber>46</ColumnNumber>
    <OriginalText>Arial</OriginalText>
    <IsHidden>false</IsHidden>
    <IndexOnLine>1</IndexOnLine>
    <StartOfStatement>96</StartOfStatement>
    <EndOfStatement>97</EndOfStatement>
    <IsVerbatim>false</IsVerbatim>
    <IsHiddenBlock>false</IsHiddenBlock>
    <CodeElement>PrnDoc_PrintPage</CodeElement>
    <RelativeLineNumber>15</RelativeLineNumber>
    <IsHiddenString>false</IsHiddenString>
    <IsInterpolatedString>false</IsInterpolatedString>
    <ClassName>PfsenseVoucherMgr.frmShowVoucher</ClassName>
    <IsController>false</IsController>
  </SourceScanResults>
  <SourceScanResults>
    <SourceScanID>75</SourceScanID>
    <ModuleName>frmShowVoucher.cs</ModuleName>
    <LineNumber>101</LineNumber>
    <ColumnNumber>45</ColumnNumber>
    <OriginalText>Arial</OriginalText>
    <IsHidden>false</IsHidden>
    <IndexOnLine>0</IndexOnLine>
    <StartOfStatement>100</StartOfStatement>
    <EndOfStatement>101</EndOfStatement>
    <IsVerbatim>false</IsVerbatim>
    <IsHiddenBlock>false</IsHiddenBlock>
    <CodeElement>PrnDoc_PrintPage</CodeElement>
    <RelativeLineNumber>19</RelativeLineNumber>
    <IsHiddenString>false</IsHiddenString>
    <IsInterpolatedString>false</IsInterpolatedString>
    <ClassName>PfsenseVoucherMgr.frmShowVoucher</ClassName>
    <IsController>false</IsController>
  </SourceScanResults>
  <SourceScanResults>
    <SourceScanID>76</SourceScanID>
    <ModuleName>frmShowVoucher.cs</ModuleName>
    <LineNumber>105</LineNumber>
    <ColumnNumber>46</ColumnNumber>
    <OriginalText>Arial</OriginalText>
    <IsHidden>false</IsHidden>
    <IndexOnLine>0</IndexOnLine>
    <StartOfStatement>104</StartOfStatement>
    <EndOfStatement>105</EndOfStatement>
    <IsVerbatim>false</IsVerbatim>
    <IsHiddenBlock>false</IsHiddenBlock>
    <CodeElement>PrnDoc_PrintPage</CodeElement>
    <RelativeLineNumber>23</RelativeLineNumber>
    <IsHiddenString>false</IsHiddenString>
    <IsInterpolatedString>false</IsInterpolatedString>
    <ClassName>PfsenseVoucherMgr.frmShowVoucher</ClassName>
    <IsController>false</IsController>
  </SourceScanResults>
  <SourceScanResults>
    <SourceScanID>77</SourceScanID>
    <ModuleName>frmShowVoucher.cs</ModuleName>
    <LineNumber>108</LineNumber>
    <ColumnNumber>36</ColumnNumber>
    <OriginalText>Generated by: </OriginalText>
    <IsHidden>false</IsHidden>
    <IndexOnLine>0</IndexOnLine>
    <StartOfStatement>108</StartOfStatement>
    <EndOfStatement>108</EndOfStatement>
    <IsVerbatim>false</IsVerbatim>
    <IsHiddenBlock>false</IsHiddenBlock>
    <CodeElement>PrnDoc_PrintPage</CodeElement>
    <RelativeLineNumber>26</RelativeLineNumber>
    <IsHiddenString>false</IsHiddenString>
    <IsInterpolatedString>false</IsInterpolatedString>
    <ClassName>PfsenseVoucherMgr.frmShowVoucher</ClassName>
    <IsController>false</IsController>
  </SourceScanResults>
  <SourceScanResults>
    <SourceScanID>78</SourceScanID>
    <ModuleName>frmShowVoucher.cs</ModuleName>
    <LineNumber>109</LineNumber>
    <ColumnNumber>46</ColumnNumber>
    <OriginalText>Arial</OriginalText>
    <IsHidden>false</IsHidden>
    <IndexOnLine>1</IndexOnLine>
    <StartOfStatement>108</StartOfStatement>
    <EndOfStatement>109</EndOfStatement>
    <IsVerbatim>false</IsVerbatim>
    <IsHiddenBlock>false</IsHiddenBlock>
    <CodeElement>PrnDoc_PrintPage</CodeElement>
    <RelativeLineNumber>27</RelativeLineNumber>
    <IsHiddenString>false</IsHiddenString>
    <IsInterpolatedString>false</IsInterpolatedString>
    <ClassName>PfsenseVoucherMgr.frmShowVoucher</ClassName>
    <IsController>false</IsController>
  </SourceScanResults>
  <SourceScanResults>
    <SourceScanID>79</SourceScanID>
    <ModuleName>UICulture.cs</ModuleName>
    <LineNumber>39</LineNumber>
    <ColumnNumber>90</ColumnNumber>
    <OriginalText>en-US</OriginalText>
    <IsHidden>false</IsHidden>
    <IndexOnLine>0</IndexOnLine>
    <StartOfStatement>39</StartOfStatement>
    <EndOfStatement>39</EndOfStatement>
    <IsVerbatim>false</IsVerbatim>
    <IsHiddenBlock>false</IsHiddenBlock>
    <CodeElement />
    <RelativeLineNumber>39</RelativeLineNumber>
    <IsHiddenString>false</IsHiddenString>
    <IsInterpolatedString>false</IsInterpolatedString>
    <ClassName>PfsenseVoucherMgr.UICulture</ClassName>
    <IsController>false</IsController>
  </SourceScanResults>
  <SourceScanResults>
    <SourceScanID>80</SourceScanID>
    <ModuleName>UICulture.cs</ModuleName>
    <LineNumber>39</LineNumber>
    <ColumnNumber>99</ColumnNumber>
    <OriginalText>de-DE</OriginalText>
    <IsHidden>false</IsHidden>
    <IndexOnLine>1</IndexOnLine>
    <StartOfStatement>39</StartOfStatement>
    <EndOfStatement>39</EndOfStatement>
    <IsVerbatim>false</IsVerbatim>
    <IsHiddenBlock>false</IsHiddenBlock>
    <CodeElement />
    <RelativeLineNumber>39</RelativeLineNumber>
    <IsHiddenString>false</IsHiddenString>
    <IsInterpolatedString>false</IsInterpolatedString>
    <ClassName>PfsenseVoucherMgr.UICulture</ClassName>
    <IsController>false</IsController>
  </SourceScanResults>
</SourceScanResultsCache>